{"events":[{"defined_class":"com.example.accesscontrol.service.UserGroupServiceTest","event":"call","id":188855,"lineno":40,"method_id":"assignUsersToGroups_success_skipsExisting","path":"src/test/java/com/example/accesscontrol/service/UserGroupServiceTest.java","receiver":{"class":"com.example.accesscontrol.service.UserGroupServiceTest","object_id":818195882,"value":"com.example.accesscontrol.service.UserGroupServiceTest@30c4adaa"},"static":false,"thread_id":1},{"defined_class":"com.example.accesscontrol.entity.UserGroup","event":"call","id":188856,"lineno":21,"method_id":"builder","path":"src/main/java/com/example/accesscontrol/entity/UserGroup.java","static":true,"thread_id":1},{"elapsed":1.3451E-4,"event":"return","id":188857,"parent_id":188856,"return_value":{"class":"com.example.accesscontrol.entity.UserGroup$UserGroupBuilder","object_id":2026872057,"value":"UserGroup.UserGroupBuilder(id=null, user=null, group=null, version=0)"},"thread_id":1},{"defined_class":"com.example.accesscontrol.entity.User","event":"call","id":188858,"lineno":22,"method_id":"builder","path":"src/main/java/com/example/accesscontrol/entity/User.java","static":true,"thread_id":1},{"elapsed":0.0,"event":"return","id":188859,"parent_id":188858,"return_value":{"class":"com.example.accesscontrol.entity.User$UserBuilder","object_id":138204893,"value":"User.UserBuilder(id=null, email=null, password=null, enabled$value=false, version=0, userRoles=null, userGroups=null)"},"thread_id":1},{"defined_class":"com.example.accesscontrol.entity.User$UserBuilder","event":"call","id":188860,"lineno":22,"method_id":"id","parameters":[{"class":"java.lang.Long","kind":"req","name":"id","object_id":642550303,"value":"1"}],"path":"src/main/java/com/example/accesscontrol/entity/User.java","receiver":{"class":"com.example.accesscontrol.entity.User$UserBuilder","object_id":138204893,"value":"User.UserBuilder(id=1, email=null, password=null, enabled$value=false, version=0, userRoles=null, userGroups=null)"},"static":false,"thread_id":1},{"elapsed":0.0,"event":"return","id":188861,"parent_id":188860,"return_value":{"class":"com.example.accesscontrol.entity.User$UserBuilder","object_id":138204893,"value":"User.UserBuilder(id=1, email=null, password=null, enabled$value=false, version=0, userRoles=null, userGroups=null)"},"thread_id":1},{"defined_class":"com.example.accesscontrol.entity.User$UserBuilder","event":"call","id":188862,"lineno":22,"method_id":"build","path":"src/main/java/com/example/accesscontrol/entity/User.java","receiver":{"class":"com.example.accesscontrol.entity.User$UserBuilder","object_id":138204893,"value":"User.UserBuilder(id=1, email=null, password=null, enabled$value=false, version=0, userRoles=null, userGroups=null)"},"static":false,"thread_id":1},{"elapsed":0.0,"event":"return","id":188863,"parent_id":188862,"return_value":{"class":"com.example.accesscontrol.entity.User","object_id":575580823,"value":"User(id=1, email=null, password=null, enabled=true, version=0)"},"thread_id":1},{"defined_class":"com.example.accesscontrol.entity.UserGroup$UserGroupBuilder","event":"call","id":188864,"lineno":21,"method_id":"user","parameters":[{"class":"com.example.accesscontrol.entity.User","kind":"req","name":"user","object_id":575580823,"value":"User(id=1, email=null, password=null, enabled=true, version=0)"}],"path":"src/main/java/com/example/accesscontrol/entity/UserGroup.java","receiver":{"class":"com.example.accesscontrol.entity.UserGroup$UserGroupBuilder","object_id":2026872057,"value":"UserGroup.UserGroupBuilder(id=null, user=User(id=1, email=null, password=null, enabled=true, version=0), group=null, version=0)"},"static":false,"thread_id":1},{"elapsed":0.0,"event":"return","id":188865,"parent_id":188864,"return_value":{"class":"com.example.accesscontrol.entity.UserGroup$UserGroupBuilder","object_id":2026872057,"value":"UserGroup.UserGroupBuilder(id=null, user=User(id=1, email=null, password=null, enabled=true, version=0), group=null, version=0)"},"thread_id":1},{"defined_class":"com.example.accesscontrol.entity.Group","event":"call","id":188866,"lineno":19,"method_id":"builder","path":"src/main/java/com/example/accesscontrol/entity/Group.java","static":true,"thread_id":1},{"elapsed":0.0,"event":"return","id":188867,"parent_id":188866,"return_value":{"class":"com.example.accesscontrol.entity.Group$GroupBuilder","object_id":938670729,"value":"Group.GroupBuilder(id=null, name=null, version=0, userGroups=null, groupRoles=null)"},"thread_id":1},{"defined_class":"com.example.accesscontrol.entity.Group$GroupBuilder","event":"call","id":188868,"lineno":19,"method_id":"id","parameters":[{"class":"java.lang.Long","kind":"req","name":"id","object_id":203713177,"value":"10"}],"path":"src/main/java/com/example/accesscontrol/entity/Group.java","receiver":{"class":"com.example.accesscontrol.entity.Group$GroupBuilder","object_id":938670729,"value":"Group.GroupBuilder(id=10, name=null, version=0, userGroups=null, groupRoles=null)"},"static":false,"thread_id":1},{"elapsed":0.0,"event":"return","id":188869,"parent_id":188868,"return_value":{"class":"com.example.accesscontrol.entity.Group$GroupBuilder","object_id":938670729,"value":"Group.GroupBuilder(id=10, name=null, version=0, userGroups=null, groupRoles=null)"},"thread_id":1},{"defined_class":"com.example.accesscontrol.entity.Group$GroupBuilder","event":"call","id":188870,"lineno":19,"method_id":"build","path":"src/main/java/com/example/accesscontrol/entity/Group.java","receiver":{"class":"com.example.accesscontrol.entity.Group$GroupBuilder","object_id":938670729,"value":"Group.GroupBuilder(id=10, name=null, version=0, userGroups=null, groupRoles=null)"},"static":false,"thread_id":1},{"elapsed":0.0,"event":"return","id":188871,"parent_id":188870,"return_value":{"class":"com.example.accesscontrol.entity.Group","object_id":861831386,"value":"Group(id=10, name=null, version=0)"},"thread_id":1},{"defined_class":"com.example.accesscontrol.entity.UserGroup$UserGroupBuilder","event":"call","id":188872,"lineno":21,"method_id":"group","parameters":[{"class":"com.example.accesscontrol.entity.Group","kind":"req","name":"group","object_id":861831386,"value":"Group(id=10, name=null, version=0)"}],"path":"src/main/java/com/example/accesscontrol/entity/UserGroup.java","receiver":{"class":"com.example.accesscontrol.entity.UserGroup$UserGroupBuilder","object_id":2026872057,"value":"UserGroup.UserGroupBuilder(id=null, user=User(id=1, email=null, password=null, enabled=true, version=0), group=Group(id=10, name=null, version=0), version=0)"},"static":false,"thread_id":1},{"elapsed":0.0,"event":"return","id":188873,"parent_id":188872,"return_value":{"class":"com.example.accesscontrol.entity.UserGroup$UserGroupBuilder","object_id":2026872057,"value":"UserGroup.UserGroupBuilder(id=null, user=User(id=1, email=null, password=null, enabled=true, version=0), group=Group(id=10, name=null, version=0), version=0)"},"thread_id":1},{"defined_class":"com.example.accesscontrol.entity.UserGroup$UserGroupBuilder","event":"call","id":188874,"lineno":21,"method_id":"build","path":"src/main/java/com/example/accesscontrol/entity/UserGroup.java","receiver":{"class":"com.example.accesscontrol.entity.UserGroup$UserGroupBuilder","object_id":2026872057,"value":"UserGroup.UserGroupBuilder(id=null, user=User(id=1, email=null, password=null, enabled=true, version=0), group=Group(id=10, name=null, version=0), version=0)"},"static":false,"thread_id":1},{"elapsed":0.0,"event":"return","id":188875,"parent_id":188874,"return_value":{"class":"com.example.accesscontrol.entity.UserGroup","object_id":1564090962,"value":"UserGroup(id=null, version=0)"},"thread_id":1},{"defined_class":"com.example.accesscontrol.service.UserGroupService","event":"call","id":188876,"lineno":29,"method_id":"assignUsersToGroups","parameters":[{"class":"com.example.accesscontrol.dto.user.assignUsersToGroup.AssignUsersToGroupsRequest","kind":"req","name":"request","object_id":720483333,"value":"AssignUsersToGroupsRequest(userIds=[1], groupIds=[10, 11])"}],"path":"src/main/java/com/example/accesscontrol/service/UserGroupService.java","receiver":{"class":"com.example.accesscontrol.service.UserGroupService","object_id":175579504,"value":"com.example.accesscontrol.service.UserGroupService@a772170"},"static":false,"thread_id":1},{"defined_class":"com.example.accesscontrol.entity.User","event":"call","id":188877,"lineno":22,"method_id":"builder","path":"src/main/java/com/example/accesscontrol/entity/User.java","static":true,"thread_id":1},{"elapsed":1.0103E-4,"event":"return","id":188878,"parent_id":188877,"return_value":{"class":"com.example.accesscontrol.entity.User$UserBuilder","object_id":1844357585,"value":"User.UserBuilder(id=null, email=null, password=null, enabled$value=false, version=0, userRoles=null, userGroups=null)"},"thread_id":1},{"defined_class":"com.example.accesscontrol.entity.User$UserBuilder","event":"call","id":188879,"lineno":22,"method_id":"id","parameters":[{"class":"java.lang.Long","kind":"req","name":"id","object_id":642550303,"value":"1"}],"path":"src/main/java/com/example/accesscontrol/entity/User.java","receiver":{"class":"com.example.accesscontrol.entity.User$UserBuilder","object_id":1844357585,"value":"User.UserBuilder(id=1, email=null, password=null, enabled$value=false, version=0, userRoles=null, userGroups=null)"},"static":false,"thread_id":1},{"elapsed":0.0,"event":"return","id":188880,"parent_id":188879,"return_value":{"class":"com.example.accesscontrol.entity.User$UserBuilder","object_id":1844357585,"value":"User.UserBuilder(id=1, email=null, password=null, enabled$value=false, version=0, userRoles=null, userGroups=null)"},"thread_id":1},{"defined_class":"com.example.accesscontrol.entity.User$UserBuilder","event":"call","id":188881,"lineno":22,"method_id":"build","path":"src/main/java/com/example/accesscontrol/entity/User.java","receiver":{"class":"com.example.accesscontrol.entity.User$UserBuilder","object_id":1844357585,"value":"User.UserBuilder(id=1, email=null, password=null, enabled$value=false, version=0, userRoles=null, userGroups=null)"},"static":false,"thread_id":1},{"elapsed":0.0,"event":"return","id":188882,"parent_id":188881,"return_value":{"class":"com.example.accesscontrol.entity.User","object_id":1632251532,"value":"User(id=1, email=null, password=null, enabled=true, version=0)"},"thread_id":1},{"defined_class":"com.example.accesscontrol.entity.Group","event":"call","id":188883,"lineno":19,"method_id":"builder","path":"src/main/java/com/example/accesscontrol/entity/Group.java","static":true,"thread_id":1},{"elapsed":1.0012E-4,"event":"return","id":188884,"parent_id":188883,"return_value":{"class":"com.example.accesscontrol.entity.Group$GroupBuilder","object_id":1384513396,"value":"Group.GroupBuilder(id=null, name=null, version=0, userGroups=null, groupRoles=null)"},"thread_id":1},{"defined_class":"com.example.accesscontrol.entity.Group$GroupBuilder","event":"call","id":188885,"lineno":19,"method_id":"id","parameters":[{"class":"java.lang.Long","kind":"req","name":"id","object_id":1860675626,"value":"11"}],"path":"src/main/java/com/example/accesscontrol/entity/Group.java","receiver":{"class":"com.example.accesscontrol.entity.Group$GroupBuilder","object_id":1384513396,"value":"Group.GroupBuilder(id=11, name=null, version=0, userGroups=null, groupRoles=null)"},"static":false,"thread_id":1},{"elapsed":0.0,"event":"return","id":188886,"parent_id":188885,"return_value":{"class":"com.example.accesscontrol.entity.Group$GroupBuilder","object_id":1384513396,"value":"Group.GroupBuilder(id=11, name=null, version=0, userGroups=null, groupRoles=null)"},"thread_id":1},{"defined_class":"com.example.accesscontrol.entity.Group$GroupBuilder","event":"call","id":188887,"lineno":19,"method_id":"build","path":"src/main/java/com/example/accesscontrol/entity/Group.java","receiver":{"class":"com.example.accesscontrol.entity.Group$GroupBuilder","object_id":1384513396,"value":"Group.GroupBuilder(id=11, name=null, version=0, userGroups=null, groupRoles=null)"},"static":false,"thread_id":1},{"elapsed":0.0,"event":"return","id":188888,"parent_id":188887,"return_value":{"class":"com.example.accesscontrol.entity.Group","object_id":1978869949,"value":"Group(id=11, name=null, version=0)"},"thread_id":1},{"defined_class":"com.example.accesscontrol.dto.user.assignUsersToGroup.AssignUsersToGroupsResponse","event":"call","id":188889,"lineno":7,"method_id":"builder","path":"src/main/java/com/example/accesscontrol/dto/user/assignUsersToGroup/AssignUsersToGroupsResponse.java","static":true,"thread_id":1},{"elapsed":0.0,"event":"return","id":188890,"parent_id":188889,"return_value":{"class":"com.example.accesscontrol.dto.user.assignUsersToGroup.AssignUsersToGroupsResponse$AssignUsersToGroupsResponseBuilder","object_id":1842067443,"value":"AssignUsersToGroupsResponse.AssignUsersToGroupsResponseBuilder(message=null, assignedCount=0)"},"thread_id":1},{"defined_class":"com.example.accesscontrol.dto.user.assignUsersToGroup.AssignUsersToGroupsResponse$AssignUsersToGroupsResponseBuilder","event":"call","id":188891,"lineno":7,"method_id":"message","parameters":[{"class":"java.lang.String","kind":"req","name":"message","object_id":1408474504,"value":"Users assigned to groups successfully"}],"path":"src/main/java/com/example/accesscontrol/dto/user/assignUsersToGroup/AssignUsersToGroupsResponse.java","receiver":{"class":"com.example.accesscontrol.dto.user.assignUsersToGroup.AssignUsersToGroupsResponse$AssignUsersToGroupsResponseBuilder","object_id":1842067443,"value":"AssignUsersToGroupsResponse.AssignUsersToGroupsResponseBuilder(message=Users assigned to groups successfully, assignedCount=0)"},"static":false,"thread_id":1},{"elapsed":0.0,"event":"return","id":188892,"parent_id":188891,"return_value":{"class":"com.example.accesscontrol.dto.user.assignUsersToGroup.AssignUsersToGroupsResponse$AssignUsersToGroupsResponseBuilder","object_id":1842067443,"value":"AssignUsersToGroupsResponse.AssignUsersToGroupsResponseBuilder(message=Users assigned to groups successfully, assignedCount=0)"},"thread_id":1},{"defined_class":"com.example.accesscontrol.dto.user.assignUsersToGroup.AssignUsersToGroupsResponse$AssignUsersToGroupsResponseBuilder","event":"call","id":188893,"lineno":7,"method_id":"assignedCount","parameters":[{"class":"java.lang.Integer","kind":"req","name":"assignedCount","object_id":432964308,"value":"1"}],"path":"src/main/java/com/example/accesscontrol/dto/user/assignUsersToGroup/AssignUsersToGroupsResponse.java","receiver":{"class":"com.example.accesscontrol.dto.user.assignUsersToGroup.AssignUsersToGroupsResponse$AssignUsersToGroupsResponseBuilder","object_id":1842067443,"value":"AssignUsersToGroupsResponse.AssignUsersToGroupsResponseBuilder(message=Users assigned to groups successfully, assignedCount=1)"},"static":false,"thread_id":1},{"elapsed":0.0,"event":"return","id":188894,"parent_id":188893,"return_value":{"class":"com.example.accesscontrol.dto.user.assignUsersToGroup.AssignUsersToGroupsResponse$AssignUsersToGroupsResponseBuilder","object_id":1842067443,"value":"AssignUsersToGroupsResponse.AssignUsersToGroupsResponseBuilder(message=Users assigned to groups successfully, assignedCount=1)"},"thread_id":1},{"defined_class":"com.example.accesscontrol.dto.user.assignUsersToGroup.AssignUsersToGroupsResponse$AssignUsersToGroupsResponseBuilder","event":"call","id":188895,"lineno":7,"method_id":"build","path":"src/main/java/com/example/accesscontrol/dto/user/assignUsersToGroup/AssignUsersToGroupsResponse.java","receiver":{"class":"com.example.accesscontrol.dto.user.assignUsersToGroup.AssignUsersToGroupsResponse$AssignUsersToGroupsResponseBuilder","object_id":1842067443,"value":"AssignUsersToGroupsResponse.AssignUsersToGroupsResponseBuilder(message=Users assigned to groups successfully, assignedCount=1)"},"static":false,"thread_id":1},{"elapsed":0.0,"event":"return","id":188896,"parent_id":188895,"return_value":{"class":"com.example.accesscontrol.dto.user.assignUsersToGroup.AssignUsersToGroupsResponse","object_id":1573243528,"value":"AssignUsersToGroupsResponse(message=Users assigned to groups successfully, assignedCount=1)"},"thread_id":1},{"elapsed":3.0105E-4,"event":"return","id":188897,"parent_id":188876,"return_value":{"class":"com.example.accesscontrol.dto.user.assignUsersToGroup.AssignUsersToGroupsResponse","object_id":1573243528,"value":"AssignUsersToGroupsResponse(message=Users assigned to groups successfully, assignedCount=1)"},"thread_id":1},{"elapsed":7.8727E-4,"event":"return","id":188898,"parent_id":188855,"thread_id":1}],"classMap":[{"children":[{"children":[{"children":[{"children":[{"children":[{"labels":[],"location":"src/test/java/com/example/accesscontrol/service/UserGroupServiceTest.java:40","name":"assignUsersToGroups_success_skipsExisting","static":false,"type":"function"}],"location":"src/test/java/com/example/accesscontrol/service/UserGroupServiceTest.java","name":"UserGroupServiceTest","static":false,"type":"class"},{"children":[{"labels":[],"location":"src/main/java/com/example/accesscontrol/service/UserGroupService.java:29","name":"assignUsersToGroups","static":false,"type":"function"}],"location":"src/main/java/com/example/accesscontrol/service/UserGroupService.java","name":"UserGroupService","static":false,"type":"class"}],"name":"service","type":"package"},{"children":[{"children":[{"labels":[],"location":"src/main/java/com/example/accesscontrol/entity/UserGroup.java:21","name":"build","static":false,"type":"function"},{"labels":[],"location":"src/main/java/com/example/accesscontrol/entity/UserGroup.java:21","name":"user","static":false,"type":"function"},{"labels":[],"location":"src/main/java/com/example/accesscontrol/entity/UserGroup.java:21","name":"group","static":false,"type":"function"}],"location":"src/main/java/com/example/accesscontrol/entity/UserGroup.java","name":"UserGroup$UserGroupBuilder","static":true,"type":"class"},{"children":[{"labels":[],"location":"src/main/java/com/example/accesscontrol/entity/User.java:22","name":"build","static":false,"type":"function"},{"labels":[],"location":"src/main/java/com/example/accesscontrol/entity/User.java:22","name":"id","static":false,"type":"function"}],"location":"src/main/java/com/example/accesscontrol/entity/User.java","name":"User$UserBuilder","static":true,"type":"class"},{"children":[{"labels":[],"location":"src/main/java/com/example/accesscontrol/entity/UserGroup.java:21","name":"builder","static":true,"type":"function"}],"location":"src/main/java/com/example/accesscontrol/entity/UserGroup.java","name":"UserGroup","static":false,"type":"class"},{"children":[{"labels":[],"location":"src/main/java/com/example/accesscontrol/entity/Group.java:19","name":"builder","static":true,"type":"function"}],"location":"src/main/java/com/example/accesscontrol/entity/Group.java","name":"Group","static":false,"type":"class"},{"children":[{"labels":[],"location":"src/main/java/com/example/accesscontrol/entity/Group.java:19","name":"id","static":false,"type":"function"},{"labels":[],"location":"src/main/java/com/example/accesscontrol/entity/Group.java:19","name":"build","static":false,"type":"function"}],"location":"src/main/java/com/example/accesscontrol/entity/Group.java","name":"Group$GroupBuilder","static":true,"type":"class"},{"children":[{"labels":[],"location":"src/main/java/com/example/accesscontrol/entity/User.java:22","name":"builder","static":true,"type":"function"}],"location":"src/main/java/com/example/accesscontrol/entity/User.java","name":"User","static":false,"type":"class"}],"name":"entity","type":"package"},{"children":[{"children":[{"children":[{"children":[{"labels":[],"location":"src/main/java/com/example/accesscontrol/dto/user/assignUsersToGroup/AssignUsersToGroupsResponse.java:7","name":"builder","static":true,"type":"function"}],"location":"src/main/java/com/example/accesscontrol/dto/user/assignUsersToGroup/AssignUsersToGroupsResponse.java","name":"AssignUsersToGroupsResponse","static":false,"type":"class"},{"children":[{"labels":[],"location":"src/main/java/com/example/accesscontrol/dto/user/assignUsersToGroup/AssignUsersToGroupsResponse.java:7","name":"build","static":false,"type":"function"},{"labels":[],"location":"src/main/java/com/example/accesscontrol/dto/user/assignUsersToGroup/AssignUsersToGroupsResponse.java:7","name":"message","static":false,"type":"function"},{"labels":[],"location":"src/main/java/com/example/accesscontrol/dto/user/assignUsersToGroup/AssignUsersToGroupsResponse.java:7","name":"assignedCount","static":false,"type":"function"}],"location":"src/main/java/com/example/accesscontrol/dto/user/assignUsersToGroup/AssignUsersToGroupsResponse.java","name":"AssignUsersToGroupsResponse$AssignUsersToGroupsResponseBuilder","static":true,"type":"class"}],"name":"assignUsersToGroup","type":"package"}],"name":"user","type":"package"}],"name":"dto","type":"package"}],"name":"accesscontrol","type":"package"}],"name":"example","type":"package"}],"name":"com","type":"package"}],"version":"1.2","metadata":{"name":"User group service assign users to groups _ success _ skips existing","app":"accesscontrol","language":{"name":"java","version":"17.0.15+6-LTS","engine":"OpenJDK 64-Bit Server VM"},"client":{"name":"appmap-java","url":"https://github.com/appland/appmap-java"},"recorder":{"name":"junit","type":"tests"},"recording":{"defined_class":"com.example.accesscontrol.service.UserGroupServiceTest","method_id":"assignUsersToGroups_success_skipsExisting"},"git":{"repository":"https://github.com/AlhaderMajd/accessControl-majd.git","branch":"main","commit":"f969f73139297df67ef2edc2eb60357323900968"},"source_location":"src/test/java/com/example/accesscontrol/service/UserGroupServiceTest.java:40","frameworks":[{"name":"JUnit","version":"5"}],"test_status":"succeeded"},"eventUpdates":{}}