{"events":[{"defined_class":"com.example.accesscontrol.service.UserServiceTest","event":"call","id":225579,"lineno":219,"method_id":"getUserDetails_invalidIdZeroOrNull_throws","path":"src/test/java/com/example/accesscontrol/service/UserServiceTest.java","receiver":{"class":"com.example.accesscontrol.service.UserServiceTest","object_id":201831957,"value":"com.example.accesscontrol.service.UserServiceTest@c07b615"},"static":false,"thread_id":1},{"defined_class":"com.example.accesscontrol.service.UserService","event":"call","id":225580,"lineno":111,"method_id":"getUserDetails","parameters":[{"class":"java.lang.Long","kind":"req","name":"id","object_id":360393288,"value":"0"}],"path":"src/main/java/com/example/accesscontrol/service/UserService.java","receiver":{"class":"com.example.accesscontrol.service.UserService","object_id":1488928894,"value":"com.example.accesscontrol.service.UserService@58bf407e"},"static":false,"thread_id":1},{"elapsed":1.008E-4,"event":"return","exceptions":[{"class":"java.lang.IllegalArgumentException","lineno":111,"message":"Invalid user ID","object_id":1555539328,"path":"UserService.java"}],"id":225581,"parent_id":225580,"thread_id":1},{"defined_class":"com.example.accesscontrol.service.UserService","event":"call","id":225582,"lineno":111,"method_id":"getUserDetails","parameters":[{"class":"java.lang.Long","kind":"req","name":"id","object_id":0}],"path":"src/main/java/com/example/accesscontrol/service/UserService.java","receiver":{"class":"com.example.accesscontrol.service.UserService","object_id":1488928894,"value":"com.example.accesscontrol.service.UserService@58bf407e"},"static":false,"thread_id":1},{"elapsed":9.983E-5,"event":"return","exceptions":[{"class":"java.lang.IllegalArgumentException","lineno":111,"message":"Invalid user ID","object_id":1328485989,"path":"UserService.java"}],"id":225583,"parent_id":225582,"thread_id":1},{"elapsed":4.505E-4,"event":"return","id":225584,"parent_id":225579,"thread_id":1}],"classMap":[{"children":[{"children":[{"children":[{"children":[{"children":[{"labels":[],"location":"src/test/java/com/example/accesscontrol/service/UserServiceTest.java:219","name":"getUserDetails_invalidIdZeroOrNull_throws","static":false,"type":"function"}],"location":"src/test/java/com/example/accesscontrol/service/UserServiceTest.java","name":"UserServiceTest","static":false,"type":"class"},{"children":[{"labels":[],"location":"src/main/java/com/example/accesscontrol/service/UserService.java:111","name":"getUserDetails","static":false,"type":"function"}],"location":"src/main/java/com/example/accesscontrol/service/UserService.java","name":"UserService","static":false,"type":"class"}],"name":"service","type":"package"}],"name":"accesscontrol","type":"package"}],"name":"example","type":"package"}],"name":"com","type":"package"}],"version":"1.2","metadata":{"name":"User service get user details _ invalid id zero or null _ throws","app":"accesscontrol","language":{"name":"java","version":"17.0.15+6-LTS","engine":"OpenJDK 64-Bit Server VM"},"client":{"name":"appmap-java","url":"https://github.com/appland/appmap-java"},"recorder":{"name":"junit","type":"tests"},"recording":{"defined_class":"com.example.accesscontrol.service.UserServiceTest","method_id":"getUserDetails_invalidIdZeroOrNull_throws"},"git":{"repository":"https://github.com/AlhaderMajd/accessControl-majd.git","branch":"main","commit":"52348b38882c95243444f8525b39b8cad6e50a0a"},"source_location":"src/test/java/com/example/accesscontrol/service/UserServiceTest.java:219","frameworks":[{"name":"JUnit","version":"5"}],"test_status":"succeeded"},"eventUpdates":{}}